dissonant/__init__.py
dissonant/dissonance.py
dissonant/models.py
dissonant/tuning.py
dissonant-0.1.1.dist-info/DESCRIPTION.rst
dissonant-0.1.1.dist-info/METADATA
dissonant-0.1.1.dist-info/RECORD
dissonant-0.1.1.dist-info/WHEEL
dissonant-0.1.1.dist-info/metadata.json
dissonant-0.1.1.dist-info/top_level.txt
