Metadata-Version: 2.0
Name: dissonant
Version: 0.1.1
Summary: Musical chord dissonance models
Home-page: https://github.com/bzamecnik/dissonant
Author: Bohumir Zamecnik
Author-email: bohumir.zamecnik@gmail.com
License: UNKNOWN
Platform: UNKNOWN
Classifier: Development Status :: 3 - Alpha
Classifier: Intended Audience :: Developers
Classifier: Intended Audience :: Science/Research
Classifier: Topic :: Multimedia :: Sound/Audio :: Analysis
Classifier: License :: OSI Approved :: MIT License
Classifier: Programming Language :: Python :: 2
Classifier: Programming Language :: Python :: 3
Classifier: Operating System :: POSIX :: Linux
Classifier: Operating System :: MacOS :: MacOS X
Requires-Dist: numpy
